databricks/__init__.py
databricks/labs/__init__.py
databricks/labs/pylint/__about__.py
databricks/labs/pylint/__init__.py
databricks/labs/pylint/airflow.py
databricks/labs/pylint/all.py
databricks/labs/pylint/cli.py
databricks/labs/pylint/dbutils.py
databricks/labs/pylint/eradicate.py
databricks/labs/pylint/legacy.py
databricks/labs/pylint/mocking.py
databricks/labs/pylint/notebooks.py
databricks/labs/pylint/readability.py
databricks/labs/pylint/spark.py
databricks_labs_pylint-0.5.0.dist-info/METADATA
databricks_labs_pylint-0.5.0.dist-info/WHEEL
databricks_labs_pylint-0.5.0.dist-info/licenses/LICENSE
databricks_labs_pylint-0.5.0.dist-info/licenses/NOTICE
databricks_labs_pylint-0.5.0.dist-info/RECORD
