Metadata-Version: 2.3
Name: databricks-labs-pylint
Version: 0.5.0
Summary: Plugin for PyLint to support Databricks specific code patterns and best practices.
Project-URL: Issues, https://github.com/databrickslabs/pylint-plugin/issues
Project-URL: Source, https://github.com/databrickslabs/pylint-plugin
Author-email: Serge Smertin <serge.smertin@databricks.com>
License-File: LICENSE
License-File: NOTICE
Keywords: Databricks
Classifier: Development Status :: 3 - Alpha
Classifier: License :: Other/Proprietary License
Classifier: Programming Language :: Python
Classifier: Programming Language :: Python :: 3.8
Classifier: Programming Language :: Python :: 3.9
Classifier: Programming Language :: Python :: 3.10
Classifier: Programming Language :: Python :: 3.11
Classifier: Programming Language :: Python :: 3.12
Classifier: Programming Language :: Python :: Implementation :: CPython
Requires-Python: >=3.8
Requires-Dist: astroid
Requires-Dist: databricks-sdk
Requires-Dist: eradicate~=2.3.0
Requires-Dist: pylint
